counter-2/counter.v
/*
Author: Sajeed Mohammad Shahriat
Affiliation: Rochester Institute of Technology
All rights reserved
This files can be reused and modified given that this copyright notice is not removed
*/

module counter (
	clk,		//clock input of the design
	reset,		// active high synchrnous reset input
	enable,		// active high enable signal for counter
	counter_out	// 4 bit vector output of the counter
); //end of port list

//------------------------input ports--------------------------------

input clk ;
input reset ;
input enable;

//------------------------output ports-------------------------------

output [3:0] counter_out;

//--------------------input port data types--------------------------

wire clk;
wire reset;
wire enable;

//-------------------output port data types--------------------------

reg [3:0] counter_out;

//--------------------------RTL design-------------------------------

always @ (posedge clk)
begin :COUNTER // block name
	if (reset == 1'b1)	//reset high
		begin
			counter_out <= #1 4'b0000;
		end
	else if (enable == 1'b1)	//counter active
		begin
			counter_out <= #1 counter_out + 1;
		end
end // end of block COUNTER
endmodule // counter

counter-2/counter_tb.v
/*
Author: Sajeed Mohammad Shahriat
Affiliation: Rochester Institute of Technology
All rights reserved
This files can be reused and modified given that this copyright notice is not removed
*/

module counter_tb ();

reg clk, reset, enable; // declare all inputs as registers

wire [3:0] counter_out; // declare all outputs as wires

// clock generator
always
	begin
		#5 clk = ~clk; // toggle clock every 5 ticks
	end
//initialize all variables

initial
	begin
		
		$dumpfile("counter_wave.vcd"); // required for gtkwaveform
		$dumpvars(0,counter_tb); // required for gtkwaveform

		$display ("time\t clk reset enable counter");
		$monitor ("%g\t %b %b %b %b", $time, clk, reset, enable, counter_out);
		clk = 1; //initial value of clock
		reset = 0; // initial value of reset
		#5 reset = 1; //assert the reset
		#10 reset = 0; //de-assert the reset
		#5 enable = 1; //assert enable
		#100 enable = 0; // de-assert enable
		#10 $finish; // terminate simulation
	end
//connect DUT to test bench
counter connect_counter(
	clk,
	reset,
	enable,
	counter_out
);
endmodule

counter-2/counter_wave.vcd
$date
	Wed Jun  7 20:10:00 2017
$end
$version
	Icarus Verilog
$end
$timescale
	1s
$end
$scope module counter_tb $end
$var wire 4 ! counter_out [3:0] $end
$var reg 1 " clk $end
$var reg 1 # enable $end
$var reg 1 $ reset $end
$scope module connect_counter $end
$var wire 1 % clk $end
$var wire 1 & enable $end
$var wire 1 ' reset $end
$var reg 4 ( counter_out [3:0] $end
$scope begin COUNTER $end
$upscope $end
$upscope $end
$upscope $end
$enddefinitions $end
#0
$dumpvars
bx (
0'
x&
1%
0$
x#
1"
bx !
$end
#5
1$
1'
0"
0%
#10
1"
1%
#11
b0 (
b0 !
#15
0"
0%
0$
0'
#20
1"
1%
1#
1&
#21
b1 (
b1 !
#25
0"
0%
#30
1"
1%
#31
b10 (
b10 !
#35
0"
0%
#40
1"
1%
#41
b11 (
b11 !
#45
0"
0%
#50
1"
1%
#51
b100 (
b100 !
#55
0"
0%
#60
1"
1%
#61
b101 (
b101 !
#65
0"
0%
#70
1"
1%
#71
b110 (
b110 !
#75
0"
0%
#80
1"
1%
#81
b111 (
b111 !
#85
0"
0%
#90
1"
1%
#91
b1000 (
b1000 !
#95
0"
0%
#100
1"
1%
#101
b1001 (
b1001 !
#105
0"
0%
#110
1"
1%
#111
b1010 (
b1010 !
#115
0"
0%
#120
1"
1%
0#
0&
